{"projects":[{"id":"d543a72a-40bc-4f7e-a64f-ee321fb9a5a3","name":"yo","lastSuccessful":false,"pid":-1,"repo":{"id":"4fb7544d-bdb3-45a6-a650-bf45ae373c66","enabled":false,"source":"","branch":""},"isRunning":false,"createdOn":"2018-03-17T13:00:46.729Z","updatedOn":"2018-03-17T13:00:46.729Z","shellTask":{"id":"3b492596-cafd-4ec9-9f62-9611f3f61b84","updatedOn":"2018-03-17T13:00:46.729Z","createdOn":"2018-03-17T13:00:46.729Z","script":""}},{"id":"240a1d56-33bd-4313-ad62-c7b0d74558f2","name":"test_name","lastSuccessful":false,"pid":-1,"repo":{"id":"00abae60-ea67-425b-b90d-744bc1aacce0","enabled":false,"source":"","branch":""},"isRunning":false,"createdOn":"2018-03-17T13:00:46.967Z","updatedOn":"2018-03-17T13:00:46.967Z","shellTask":{"id":"d548c290-682b-4cc4-a632-002167e06c84","updatedOn":"2018-03-17T13:00:46.967Z","createdOn":"2018-03-17T13:00:46.967Z","script":""}}]}