{"projects":[{"id":"db0f696b-7cf7-4348-b50a-5e70fc5dffab","name":"yo","lastSuccessful":false,"pid":-1,"repo":{"id":"88e3d5ae-c288-4fc8-afce-49f21d013f22","enabled":false,"source":"","branch":""},"isRunning":false,"createdOn":"2017-07-04T02:53:58.229Z","updatedOn":"2017-07-04T02:53:58.229Z","shellTask":{"id":"2c5e2962-a14c-49c7-8725-37ee1d220ea8","updatedOn":"2017-07-04T02:53:58.229Z","createdOn":"2017-07-04T02:53:58.229Z","script":""}},{"id":"e133b15f-d832-4c96-854e-305c67f0c636","name":"test_name","lastSuccessful":false,"pid":-1,"repo":{"id":"3dc4a178-bfd0-456c-a6d1-c180e6316703","enabled":false,"source":"","branch":""},"isRunning":false,"createdOn":"2017-07-04T02:53:58.437Z","updatedOn":"2017-07-04T02:53:58.437Z","shellTask":{"id":"50d11939-b0cc-4fb1-8466-98b192d14e2f","updatedOn":"2017-07-04T02:53:58.437Z","createdOn":"2017-07-04T02:53:58.437Z","script":""}}]}